django_fever_notifications-0.1.3.dist-info/DESCRIPTION.rst
django_fever_notifications-0.1.3.dist-info/METADATA
django_fever_notifications-0.1.3.dist-info/RECORD
django_fever_notifications-0.1.3.dist-info/WHEEL
django_fever_notifications-0.1.3.dist-info/metadata.json
django_fever_notifications-0.1.3.dist-info/top_level.txt
fevernotifications/__init__.py
fevernotifications/dummy_settings.py
fevernotifications/models.py
fevernotifications/shortcuts.py
fevernotifications/migrations/0001_initial.py
fevernotifications/migrations/__init__.py
fevernotifications/static/css/fevernotifications.css
fevernotifications/static/js/fevernotifications.js
fevernotifications/templates/fevernotifications/base.html
