Metadata-Version: 2.0
Name: django-fever-notifications
Version: 0.1.3
Summary: Generic models for implement message based features
Home-page: https://github.com/Feverup/django-fever-notifications
Author: Diego Navarro Mellen
Author-email: dnmellen@gmail.com
License: BSD
Keywords: django-fever-notifications
Platform: UNKNOWN
Classifier: Development Status :: 3 - Alpha
Classifier: Framework :: Django
Classifier: Framework :: Django :: 1.8
Classifier: Framework :: Django :: 1.9
Classifier: Intended Audience :: Developers
Classifier: License :: OSI Approved :: BSD License
Classifier: Natural Language :: English
Classifier: Programming Language :: Python :: 2
Classifier: Programming Language :: Python :: 2.7
Classifier: Programming Language :: Python :: 3
Classifier: Programming Language :: Python :: 3.3
Classifier: Programming Language :: Python :: 3.4
Classifier: Programming Language :: Python :: 3.5
